{
  "root": {
    "children": [
      {
        "children": [
          {
            "detail": 0,
            "format": 0,
            "mode": "normal",
            "style": "",
            "text": "Test",
            "type": "text",
            "version": 1
          }
        ],
        "direction": "ltr",
        "format": "",
        "indent": 0,
        "type": "heading",
        "version": 1,
        "tag": "h1"
      },
      {
        "children": [
          {
            "detail": 0,
            "format": 0,
            "mode": "normal",
            "style": "",
            "text": "Voici un ",
            "type": "text",
            "version": 1
          },
          {
            "children": [
              {
                "detail": 0,
                "format": 0,
                "mode": "normal",
                "style": "",
                "text": "lien vers Google",
                "type": "text",
                "version": 1
              }
            ],
            "direction": "ltr",
            "format": "",
            "indent": 0,
            "type": "link",
            "version": 1,
            "rel": null,
            "target": null,
            "title": null,
            "url": "https://google.fr/"
          },
          {
            "detail": 0,
            "format": 0,
            "mode": "normal",
            "style": "",
            "text": ".",
            "type": "text",
            "version": 1
          }
        ],
        "direction": "ltr",
        "format": "",
        "indent": 0,
        "type": "paragraph",
        "version": 1
      }
    ],
    "direction": "ltr",
    "format": "",
    "indent": 0,
    "type": "root",
    "version": 1
  }
}
